filterkit/__init__.py
filterkit/core/__init__.py
filterkit/core/blending.py
filterkit/core/convolution.py
filterkit/core/dithering.py
filterkit/core/filters_misc.py
filterkit/core/lut_from_cube.py
filterkit/core/pillow_misc.py
filterkit/core/quantizing.py
filterkit/core/smoothing.py
filterkit/core/transforms.py
filterkit/tools/__init__.py
filterkit/tools/common.py
filterkit/tools/kernel_gen.py
filterkit-0.1.3.dist-info/LICENSE
filterkit-0.1.3.dist-info/METADATA
filterkit-0.1.3.dist-info/WHEEL
filterkit-0.1.3.dist-info/top_level.txt
filterkit-0.1.3.dist-info/RECORD
