Metadata-Version: 2.1
Name: filterkit
Version: 0.1.3
Summary: A library with efficient implementations for various image processing methods.
Home-page: https://github.com/mfarhanz/filterkit
Author: Farhan Zia
License: MIT
Classifier: Programming Language :: Python :: 3
Classifier: License :: OSI Approved :: MIT License
Classifier: Operating System :: OS Independent
Requires-Python: >=3.8
License-File: LICENSE
Requires-Dist: pillow
Requires-Dist: numba
